AUTHORS.rst
CONTRIBUTING.rst
HISTORY.rst
LICENSE
MANIFEST.in
README.rst
setup.cfg
setup.py
docs/Makefile
docs/authors.rst
docs/conf.py
docs/contributing.rst
docs/history.rst
docs/index.rst
docs/installation.rst
docs/make.bat
docs/modules.rst
docs/readme.rst
docs/usage.rst
regressors/__init__.py
regressors/_utils.py
regressors/plots.py
regressors/regressors.py
regressors/stats.py
regressors.egg-info/PKG-INFO
regressors.egg-info/SOURCES.txt
regressors.egg-info/dependency_links.txt
regressors.egg-info/not-zip-safe
regressors.egg-info/pbr.json
regressors.egg-info/requires.txt
regressors.egg-info/top_level.txt
tests/__init__.py
tests/test_regressors.py