Metadata-Version: 1.1
Name: regressors
Version: 0.0.3
Summary: Easy utilities for fitting various regressors, extracting stats, and making relevant plots
Home-page: https://github.com/nsh87/regressors
Author: Nikhil Haas
Author-email: nikhil@nikhilhaas.com
License: ISCL
Keywords: regression,lasso,ridge,principal components regression,elastic net,linear model
Platform: UNKNOWN
Classifier: Development Status :: 2 - Pre-Alpha
Classifier: Intended Audience :: Developers
Classifier: License :: OSI Approved :: ISC License (ISCL)
Classifier: Natural Language :: English
Classifier: Programming Language :: Python :: 2
Classifier: Programming Language :: Python :: 2.6
Classifier: Programming Language :: Python :: 2.7
Classifier: Programming Language :: Python :: 3
Classifier: Programming Language :: Python :: 3.3
Classifier: Programming Language :: Python :: 3.4
